{
    "total_attractors": 4,
    "size_1_attractors": 2,
    "attractors": [
        {
            "size": 1,
            "nodes": [
                "011100"
            ]
        },
        {
            "size": 6,
            "nodes": [
                "010001",
                "100100",
                "110011",
                "110101",
                "001000",
                "001001"
            ]
        },
        {
            "size": 3,
            "nodes": [
                "011000",
                "100000",
                "110001"
            ]
        },
        {
            "size": 1,
            "nodes": [
                "110000"
            ]
        }
    ]
}