{
    "total_attractors": 5,
    "size_1_attractors": 3,
    "attractors": [
        {
            "size": 3,
            "nodes": [
                "010000",
                "010101",
                "110101"
            ]
        },
        {
            "size": 1,
            "nodes": [
                "011101"
            ]
        },
        {
            "size": 2,
            "nodes": [
                "011000",
                "111101"
            ]
        },
        {
            "size": 1,
            "nodes": [
                "011110"
            ]
        },
        {
            "size": 1,
            "nodes": [
                "110100"
            ]
        }
    ]
}