{
    "total_attractors": 5,
    "size_1_attractors": 2,
    "attractors": [
        {
            "size": 4,
            "nodes": [
                "001100",
                "100000",
                "100101",
                "100111"
            ]
        },
        {
            "size": 4,
            "nodes": [
                "100001",
                "100100",
                "101101",
                "110111"
            ]
        },
        {
            "size": 2,
            "nodes": [
                "010101",
                "000011"
            ]
        },
        {
            "size": 1,
            "nodes": [
                "011010"
            ]
        },
        {
            "size": 1,
            "nodes": [
                "111010"
            ]
        }
    ]
}