{
    "total_attractors": 4,
    "size_1_attractors": 3,
    "attractors": [
        {
            "size": 3,
            "nodes": [
                "0001",
                "1111",
                "0010"
            ]
        },
        {
            "size": 1,
            "nodes": [
                "0011"
            ]
        },
        {
            "size": 1,
            "nodes": [
                "0111"
            ]
        },
        {
            "size": 1,
            "nodes": [
                "1010"
            ]
        }
    ]
}