{
    "total_attractors": 3,
    "size_1_attractors": 0,
    "attractors": [
        {
            "size": 4,
            "nodes": [
                "0010110",
                "0101011",
                "0000111",
                "1011010"
            ]
        },
        {
            "size": 2,
            "nodes": [
                "0011100",
                "0100110"
            ]
        },
        {
            "size": 7,
            "nodes": [
                "1110111",
                "0000010",
                "0110000",
                "1000010",
                "1000110",
                "1001011",
                "1010110"
            ]
        }
    ]
}